perturbvi/__init__.py
perturbvi/_version.py
perturbvi/annotation.py
perturbvi/cli.py
perturbvi/common.py
perturbvi/factorloadings.py
perturbvi/guide.py
perturbvi/infer.py
perturbvi/io.py
perturbvi/log.py
perturbvi/sim.py
perturbvi/sparse.py
perturbvi/utils.py
perturbvi-0.2.3.dist-info/METADATA
perturbvi-0.2.3.dist-info/WHEEL
perturbvi-0.2.3.dist-info/entry_points.txt
perturbvi-0.2.3.dist-info/licenses/LICENSE.txt
perturbvi-0.2.3.dist-info/RECORD
