Metadata-Version: 2.4
Name: perturbvi
Version: 0.2.3
Summary: Infer regulatory modules through informative latent component model in the single-cell Perturb-seq data
Project-URL: Documentation, https://mancusolab.github.io/perturbvi
Project-URL: Issues, https://github.com/mancusolab/perturbvi/issues
Project-URL: Source, https://github.com/mancusolab/perturbvi
Author-email: Dong Yuan <dongyuan@usc.edu>, Abdullah Al-Nahid <alnahid@usc.edu>, Nicholas Mancuso <nmancuso@usc.edu>
License-Expression: MIT
License-File: LICENSE.txt
Classifier: Development Status :: 4 - Beta
Classifier: Programming Language :: Python
Classifier: Programming Language :: Python :: 3.9
Classifier: Programming Language :: Python :: 3.10
Classifier: Programming Language :: Python :: 3.11
Classifier: Programming Language :: Python :: Implementation :: CPython
Classifier: Programming Language :: Python :: Implementation :: PyPy
Requires-Python: >=3.9
Requires-Dist: adjusttext
Requires-Dist: equinox
Requires-Dist: importlib-metadata; python_version < '3.8'
Requires-Dist: jax
Requires-Dist: jaxlib
Requires-Dist: jaxtyping
Requires-Dist: lineax
Requires-Dist: matplotlib
Requires-Dist: numpy
Requires-Dist: optax
Requires-Dist: optimistix
Requires-Dist: pandas
Requires-Dist: plum-dispatch
Requires-Dist: scanpy
Requires-Dist: seaborn
